sneakersaio/__init__.py
sneakersaio/quicktask.py
sneakers_quick_task-1.0.4.dist-info/LICENSE.txt
sneakers_quick_task-1.0.4.dist-info/METADATA
sneakers_quick_task-1.0.4.dist-info/WHEEL
sneakers_quick_task-1.0.4.dist-info/top_level.txt
sneakers_quick_task-1.0.4.dist-info/RECORD
