Metadata-Version: 2.1
Name: sneakers-quick-task
Version: 1.0.4
Summary: A simple API for generating Sneakers AIO Quick Task URLs.
Home-page: https://sneakersaio.com
Author: Sneakers AIO, Inc.
License: UNKNOWN
Project-URL: Bug Reports, https://github.com/Sneakers-AIO/Sneakers-AIO-Quick-Task-API/issues
Project-URL: Source, https://github.com/Sneakers-AIO/Sneakers-AIO-Quick-Task-API
Keywords: sneakers,aio,quick,task,url
Platform: UNKNOWN
Classifier: Development Status :: 4 - Beta
Classifier: Intended Audience :: Developers
Classifier: Topic :: Software Development :: Libraries :: Python Modules
Classifier: License :: OSI Approved :: MIT License
Classifier: Programming Language :: Python :: 3
Classifier: Programming Language :: Python :: 3.6
Classifier: Programming Language :: Python :: 3.7
Classifier: Programming Language :: Python :: 3.8
Classifier: Programming Language :: Python :: 3.9
Classifier: Programming Language :: Python :: 3 :: Only
Requires-Python: >=3.0, <4
License-File: LICENSE.txt
